setup.py
condor/__init__.py
condor/cache.py
condor/defaults.py
condor/log.py
condor/messages.py
condor/raw.py
condor/work.py
condor/examples/__init__.py
condor/examples/squares.py
condor/managers/__init__.py
condor/managers/distributed.py
condor/managers/http_status.py
condor/managers/parallel.py
condor/managers/serial.py
scripts/utcondor-ipcluster
scripts/utcondor-run
utcondor.egg-info/PKG-INFO
utcondor.egg-info/SOURCES.txt
utcondor.egg-info/dependency_links.txt
utcondor.egg-info/requires.txt
utcondor.egg-info/top_level.txt