Metadata-Version: 1.1
Name: utcondor
Version: 0.4.2
Summary: tools for distributed computing at UTCS
Home-page: https://github.com/bsilverthorn/utcondor
Author: Bryan Silverthorn
Author-email: bcs@cargo-cult.org
License: MIT
Keywords: distributed condor UT UTexas cluster
Platform: UNKNOWN
Classifier: Development Status :: 4 - Beta
Classifier: Operating System :: Unix
Classifier: Programming Language :: Python :: 2.6
Classifier: Topic :: Software Development :: Libraries
Classifier: Topic :: Utilities
